armw/__init__.py
armw/_version.py
armw/base_node.py
armw/base_parameter_server.py
armw/doc_int_enum.py
armw/globals.py
armw/ros_common.py
armw/ros1/__init__.py
armw/ros1/ddynamic_reconfigure.py
armw/ros1/inspect.py
armw/ros1/interfaces.py
armw/ros1/ros1_node.py
armw/ros1/ros1_parameter_server.py
armw/ros2/__init__.py
armw/ros2/inspect.py
armw/ros2/interfaces.py
armw/ros2/ros2_node.py
armw/ros2/ros2_parameter_server.py
armw/ros2/time.py
armw/ros2/util.py
armw/ros2/wait_for_message.py
armw-1.2.3.dist-info/METADATA
armw-1.2.3.dist-info/WHEEL
armw-1.2.3.dist-info/top_level.txt
armw-1.2.3.dist-info/RECORD
