Metadata-Version: 2.4
Name: armw
Version: 1.2.3
Summary: ARMW: Agnostic Robot MiddleWare
Author-email: Nathan McGuire <nmcguire@whoi.edu>
Maintainer-email: Caileigh Fitzgerald <cfitzgerald@whoi.edu>, Eric Gallimore <egallimore@whoi.edu>
Project-URL: Homepage, http://acomms.whoi.edu
Project-URL: Documentation, https://ros.pages.whoi.edu/armw/
Project-URL: Repository, https://git.whoi.edu/ros/armw.git
Project-URL: Issues, https://git.whoi.edu/ros/armw/-/issues
Project-URL: Changelog, https://git.whoi.edu/ros/armw/-/blob/main/CHANGELOG.md?ref_type=heads
Keywords: Library,Python Modules,Scientific/Engineering
Classifier: Development Status :: 5 - Production/Stable
Classifier: Intended Audience :: Developers
Classifier: Intended Audience :: Science/Research
Classifier: Programming Language :: Python :: 3.6
Classifier: Topic :: Software Development :: Libraries :: Python Modules
Classifier: Topic :: Scientific/Engineering
Classifier: License :: OSI Approved :: GNU Lesser General Public License v3 or later (LGPLv3+)
Requires-Python: >=3.6
